ceon_render/__init__.py
ceon_render/_app_factory.py
ceon_render/_pipeline_input.py
ceon_render/_render_settings.py
ceon_render/file_reference.py
ceon_render/job_progress.py
ceon_render/render_app.py
ceon_render/render_pipeline.py
ceon_render/render_provider.py
ceon_render/render_settings.py
ceon_render/render_apps/README.md
ceon_render/render_apps/__init__.py
ceon_render/render_apps/ffmpeg.py
ceon_render/render_apps/houdini.py
ceon_render/render_providers/README.md
ceon_render/render_providers/__init__.py
ceon_render/render_providers/conductor/README.md
ceon_render/render_providers/conductor/conductor_util.py
ceon_render/render_providers/conductor/render_provider_conductor.py
ceon_render/render_providers/conductor/setup_houdini_env.sh
ceon_render/render_providers/conductor/submit_render_to_conductor.py
ceon_render/render_providers/conductor/app_handlers/README.md
ceon_render/render_providers/conductor/app_handlers/__init__.py
ceon_render/render_providers/conductor/app_handlers/_hou_render_manager.py
ceon_render/render_providers/conductor/app_handlers/conductor_payload.py
ceon_render/render_providers/conductor/app_handlers/houdini.py
ceon_render/render_providers/conductor/app_handlers/hython_render.py
ceon_render/render_providers/conductor/app_handlers/submit.py
ceon_render/render_providers/conductor/app_handlers/submit_hou.py
ceon_render/render_providers/local/README.md
ceon_render/render_providers/local/__init__.py
ceon_render/render_providers/local/_ceon_to_local.py
ceon_render/render_providers/local/ffmpeg.py
ceon_render/render_providers/local/houdini.py
ceon_render/render_providers/local/render_provider_local.py
ceon_render/render_providers/local_blocking/README.md
ceon_render/render_providers/local_blocking/render_provider_local_blocking.py
ceon_render/render_providers/local_blocking/app_handlers/README.md
ceon_render/render_providers/local_blocking/app_handlers/__init__.py
ceon_render/render_providers/local_blocking/app_handlers/execute.py
ceon_render-0.3.0.dist-info/METADATA
ceon_render-0.3.0.dist-info/WHEEL
ceon_render-0.3.0.dist-info/RECORD
